dice.v
module dice(
    input clk,
    input rst,
    input button,
    output reg [6:0] led   // 7-segment display output
);

    reg [2:0] dice_value;  // stores dice number (1–6)
    reg [15:0] counter;    // simple pseudo-random counter

    // 7-segment encoding for numbers 1–6
    //   segments: {a,b,c,d,e,f,g}
    //   0 = ON, 1 = OFF (active-low common anode)
    function [6:0] seg_encode;
        input [2:0] num;
        case (num)
            3'd1: seg_encode = 7'b1111001; // 1
            3'd2: seg_encode = 7'b0100100; // 2
            3'd3: seg_encode = 7'b0110000; // 3
            3'd4: seg_encode = 7'b0011001; // 4
            3'd5: seg_encode = 7'b0010010; // 5
            3'd6: seg_encode = 7'b0000010; // 6
            default: seg_encode = 7'b1000000; // 0 (not used)
        endcase
    endfunction

    // Counter for randomness
    always @(posedge clk or posedge rst) begin
        if (rst)
            counter <= 0;
        else
            counter <= counter + 1;
    end

    // On button press, capture dice value
    always @(posedge clk or posedge rst) begin
        if (rst) begin
            dice_value <= 1;
            led <= seg_encode(3'd1);
        end else if (button) begin
            // Randomized dice value using urandom
            dice_value <= $urandom_range(1,6);
            led <= seg_encode(dice_value);
        end
    end

endmodule

dice_tb.v
`timescale 1ns/1ps
module dice_tb;

  reg clk;
  reg rst;
  reg button;
  wire [6:0] led;   // for 7-seg LED output
  integer file;
  integer seed;     // new: seed variable for randomness

  // Instantiate dice module
  dice uut (
    .clk(clk),
    .rst(rst),
    .button(button),
    .led(led)
  );

  // Clock generation
  always #5 clk = ~clk;

  initial begin
    // Create dumpfile for GTKWave
    $dumpfile("dump.vcd");  
    $dumpvars(0, dice_tb);
    $display("Time\tclk\tbutton\tdice_value\tLED");
    $monitor("%0t\t%b\t%b\t%0d\t%b", $time, clk, button, uut.dice_value, led);


    // Initialize
    clk = 0;
    rst = 1;
    button = 0;

    // Get random seed from command line, or fallback
    if (!$value$plusargs("seed=%d", seed))
      seed = 32'hABCD;
    seed = $urandom(seed); // reseed RNG
    $display("Using seed = %0d", seed);

    #20 rst = 0;

    // Simulate button presses
    #50 button = 1;
    #10 button = 0;

    #100 button = 1;
    #10 button = 0;

    // Wait a bit for result to settle
    #50;

    // Write result to file
    file = $fopen("result.txt", "w");
    $fwrite(file, "%0d\n", uut.dice_value);
    $fclose(file);

    $display("Dice result written to result.txt: %0d", uut.dice_value);

    $finish;
  end

endmodule

dump.vcd
$date
	Mon Nov 17 12:58:39 2025
$end
$version
	Icarus Verilog
$end
$timescale
	1ps
$end
$scope module dice_tb $end
$var wire 7 ! led [6:0] $end
$var reg 1 " button $end
$var reg 1 # clk $end
$var reg 1 $ rst $end
$var integer 32 % file [31:0] $end
$var integer 32 & seed [31:0] $end
$scope module uut $end
$var wire 1 " button $end
$var wire 1 # clk $end
$var wire 1 $ rst $end
$var reg 16 ' counter [15:0] $end
$var reg 3 ( dice_value [2:0] $end
$var reg 7 ) led [6:0] $end
$scope function seg_encode $end
$var reg 3 * num [2:0] $end
$upscope $end
$upscope $end
$upscope $end
$enddefinitions $end
$comment Show the parameter values. $end
$dumpall
$end
#0
$dumpvars
b1 *
b1111001 )
b1 (
b0 '
b10110101000011111111111101101010 &
bx %
1$
0#
0"
b1111001 !
$end
#5000
1#
#10000
0#
#15000
1#
#20000
0#
0$
#25000
b1 '
1#
#30000
0#
#35000
b10 '
1#
#40000
0#
#45000
b11 '
1#
#50000
0#
#55000
b100 '
1#
#60000
0#
#65000
b101 '
1#
#70000
0#
1"
#75000
b110 '
b101 (
1#
#80000
0#
0"
#85000
b111 '
1#
#90000
0#
#95000
b1000 '
1#
#100000
0#
#105000
b1001 '
1#
#110000
0#
#115000
b1010 '
1#
#120000
0#
#125000
b1011 '
1#
#130000
0#
#135000
b1100 '
1#
#140000
0#
#145000
b1101 '
1#
#150000
0#
#155000
b1110 '
1#
#160000
0#
#165000
b1111 '
1#
#170000
0#
#175000
b10000 '
1#
#180000
0#
1"
#185000
b10010 !
b10010 )
b100 (
b10001 '
b101 *
1#
#190000
0#
0"
#195000
b10010 '
1#
#200000
0#
#205000
b10011 '
1#
#210000
0#
#215000
b10100 '
1#
#220000
0#
#225000
b10101 '
1#
#230000
0#
#235000
b10110 '
1#
#240000
0#
b10000000000000000000000000000011 %
